mbed_os_tools/__init__.py
mbed_os_tools/detect/__init__.py
mbed_os_tools/detect/darwin.py
mbed_os_tools/detect/linux.py
mbed_os_tools/detect/lstools_base.py
mbed_os_tools/detect/main.py
mbed_os_tools/detect/platform_database.py
mbed_os_tools/detect/windows.py
mbed_os_tools/test/__init__.py
mbed_os_tools/test/__main__.py
mbed_os_tools/test/cmake_handlers.py
mbed_os_tools/test/mbed_common_api.py
mbed_os_tools/test/mbed_coverage_api.py
mbed_os_tools/test/mbed_greentea_cli.py
mbed_os_tools/test/mbed_greentea_dlm.py
mbed_os_tools/test/mbed_greentea_hooks.py
mbed_os_tools/test/mbed_greentea_log.py
mbed_os_tools/test/mbed_report_api.py
mbed_os_tools/test/mbed_target_info.py
mbed_os_tools/test/mbed_test_api.py
mbed_os_tools/test/mbed_yotta_api.py
mbed_os_tools/test/mbed_yotta_module_parse.py
mbed_os_tools/test/tests_spec.py
mbed_os_tools/test/host_tests/__init__.py
mbed_os_tools/test/host_tests/base_host_test.py
mbed_os_tools/test/host_tests/default_auto.py
mbed_os_tools/test/host_tests/detect_auto.py
mbed_os_tools/test/host_tests/dev_null_auto.py
mbed_os_tools/test/host_tests/echo.py
mbed_os_tools/test/host_tests/hello_auto.py
mbed_os_tools/test/host_tests/rtc_auto.py
mbed_os_tools/test/host_tests/wait_us_auto.py
mbed_os_tools/test/host_tests_conn_proxy/__init__.py
mbed_os_tools/test/host_tests_conn_proxy/conn_primitive.py
mbed_os_tools/test/host_tests_conn_proxy/conn_primitive_fastmodel.py
mbed_os_tools/test/host_tests_conn_proxy/conn_primitive_remote.py
mbed_os_tools/test/host_tests_conn_proxy/conn_primitive_serial.py
mbed_os_tools/test/host_tests_conn_proxy/conn_proxy.py
mbed_os_tools/test/host_tests_logger/__init__.py
mbed_os_tools/test/host_tests_logger/ht_logger.py
mbed_os_tools/test/host_tests_plugins/__init__.py
mbed_os_tools/test/host_tests_plugins/host_test_plugins.py
mbed_os_tools/test/host_tests_plugins/host_test_registry.py
mbed_os_tools/test/host_tests_plugins/module_copy_jn51xx.py
mbed_os_tools/test/host_tests_plugins/module_copy_mbed.py
mbed_os_tools-1.8.14.dist-info/LICENSE
mbed_os_tools-1.8.14.dist-info/METADATA
mbed_os_tools-1.8.14.dist-info/WHEEL
mbed_os_tools-1.8.14.dist-info/top_level.txt
mbed_os_tools-1.8.14.dist-info/RECORD
