Metadata-Version: 2.1
Name: mbed-os-tools
Version: 1.8.14
Summary: The tools to build, test, and work with Mbed OS
Home-page: https://github.com/ARMmbed/mbed-os-tools
Author: Jimmy Brisson, Brian Daniels
Author-email: jimmy.brisson@arm.com, brian.daniels@arm.com
Maintainer: Jimmy Brisson, Brian Daniels
Maintainer-email: jimmy.brisson@arm.com, brian.daniels@arm.com
License: Apache-2.0
Platform: UNKNOWN
Classifier: Development Status :: 5 - Production/Stable
Classifier: Intended Audience :: Developers
Classifier: License :: OSI Approved :: Apache Software License
Classifier: Programming Language :: Python :: 2
Classifier: Programming Language :: Python :: 2.7
Classifier: Programming Language :: Python :: 3
Classifier: Programming Language :: Python :: 3.5
Classifier: Programming Language :: Python :: 3.6
Classifier: Programming Language :: Python :: 3.7
Classifier: Programming Language :: Python :: 3.8
Classifier: Programming Language :: Python
Classifier: Topic :: Software Development :: Build Tools
Classifier: Topic :: Software Development :: Embedded Systems
Requires-Python: >=2.7.10, !=3.0.*, !=3.1.*, !=3.2.*, !=3.3.*, !=3.4.*, <4
Requires-Dist: PySerial (<4.0,>=3.0)
Requires-Dist: requests (<3.0,>=2.0)
Requires-Dist: intelhex (<3.0,>=2.0)
Requires-Dist: future
Requires-Dist: fasteners
Requires-Dist: appdirs (<2.0,>=1.4)
Requires-Dist: junit-xml (<2.0,>=1.0)
Requires-Dist: lockfile
Requires-Dist: six (<2.0,>=1.0)
Requires-Dist: colorama (<0.5,>=0.3)
Requires-Dist: beautifulsoup4
Requires-Dist: PrettyTable (<=1.0.1) ; python_version < "3.6"
Requires-Dist: prettytable (<3.0,>=2.0) ; python_version >= "3.6"
Requires-Dist: lxml ; sys_platform == "darwin"
Provides-Extra: pyocd
Requires-Dist: pyocd (>=0.32.0) ; extra == 'pyocd'
